arcee/__init__.py
arcee/data/__init__.py
arcee/data/generate.py
arcee/data/instruction_set.py
arcee/models/__init__.py
arcee/models/lm.py
arcee_align-0.0.6.dist-info/METADATA
arcee_align-0.0.6.dist-info/WHEEL
arcee_align-0.0.6.dist-info/top_level.txt
arcee_align-0.0.6.dist-info/RECORD
