Metadata-Version: 2.1
Name: arcee-align
Version: 0.0.6
Summary: The open source toolkit for finetuning and deploying LLMs
Home-page: https://arcee.ai/
Author: Arcee
Author-email: jacob@arcee.ai
License: UNKNOWN
Platform: UNKNOWN
Classifier: Programming Language :: Python :: 3
Classifier: License :: OSI Approved :: MIT License
Classifier: Operating System :: OS Independent
Requires-Python: >=3.7
Requires-Dist: accelerate (==0.20.1)
Requires-Dist: datasets (==2.12.0)
Requires-Dist: langchain (==0.0.198)
Requires-Dist: openai (==0.27.8)
Requires-Dist: peft (==0.3.0)
Requires-Dist: transformers (==4.30.1)
Requires-Dist: trl (==0.4.6)
Provides-Extra: dev
Requires-Dist: black (==22.3.0) ; extra == 'dev'
Requires-Dist: flake8 ; extra == 'dev'
Requires-Dist: isort ; extra == 'dev'
Requires-Dist: pytest ; extra == 'dev'
Requires-Dist: twine ; extra == 'dev'
Requires-Dist: wheel ; extra == 'dev'
